traceai_anthropic/__init__.py
traceai_anthropic/_stream.py
traceai_anthropic/_utils.py
traceai_anthropic/_with_span.py
traceai_anthropic/_wrappers.py
traceai_anthropic/version.py
traceai_anthropic-0.1.9.dist-info/METADATA
traceai_anthropic-0.1.9.dist-info/WHEEL
traceai_anthropic-0.1.9.dist-info/RECORD
