Metadata-Version: 2.3
Name: traceAI-anthropic
Version: 0.1.9
Summary: OpenTelemetry instrumentation for Anthropic
Author: Future AGI
Author-email: no-reply@futureagi.com
Requires-Python: >3.9,<3.14
Classifier: Programming Language :: Python :: 3
Classifier: Programming Language :: Python :: 3.10
Classifier: Programming Language :: Python :: 3.11
Classifier: Programming Language :: Python :: 3.12
Classifier: Programming Language :: Python :: 3.13
Requires-Dist: anthropic (>=0.41.0)
Requires-Dist: fi-instrumentation-otel (>=0.1.7)
